setup.py
asciinema/__init__.py
asciinema/__main__.py
asciinema/api.py
asciinema/asciicast.py
asciinema/config.py
asciinema/http_adapter.py
asciinema/player.py
asciinema/pty_recorder.py
asciinema/recorder.py
asciinema/stdout.py
asciinema/term.py
asciinema/urllib_http_adapter.py
asciinema/commands/__init__.py
asciinema/commands/auth.py
asciinema/commands/command.py
asciinema/commands/play.py
asciinema/commands/record.py
asciinema/commands/upload.py
codelynx/__init__.py
codelynx/__main__.py
codelynx/api.py
codelynx/commands/__init__.py
codelynx/commands/ask.py
codelynx/commands/lookup.py
xirion.egg-info/PKG-INFO
xirion.egg-info/SOURCES.txt
xirion.egg-info/dependency_links.txt
xirion.egg-info/entry_points.txt
xirion.egg-info/requires.txt
xirion.egg-info/top_level.txt